{"cameraMode":{"drawMode":0,"name":"Shaded","section":"Shading Mode"},"sceneLighting":true,"audioPlay":false,"sceneViewState":{"m_AlwaysRefresh":false,"showFog":true,"showSkybox":true,"showFlares":true,"showImageEffects":true,"showParticleSystems":true,"showVisualEffectGraphs":true,"m_FxEnabled":true},"in2DMode":false,"pivot":{"x":3.9045867919921877,"y":2.0401253700256349,"z":-3.951192855834961},"rotation":{"x":-0.04167890548706055,"y":0.9559836983680725,"z":-0.16834565997123719,"w":-0.23668181896209718},"size":10.0,"orthographic":false}